<annotation>
	<folder>dats</folder>
	<filename>images_062.jpeg</filename>
	<path>/media/sooryakiran/SooryaSayoo/Abhiyaan/Dataset/dats/images_062.jpeg</path>
	<source>
		<database>Unknown</database>
	</source>
	<size>
		<width>236</width>
		<height>214</height>
		<depth>3</depth>
	</size>
	<segmented>0</segmented>
	<object>
		<name>barrel</name>
		<pose>Unspecified</pose>
		<truncated>0</truncated>
		<difficult>0</difficult>
		<bndbox>
			<xmin>11</xmin>
			<ymin>147</ymin>
			<xmax>34</xmax>
			<ymax>189</ymax>
		</bndbox>
	</object>
	<object>
		<name>barrel</name>
		<pose>Unspecified</pose>
		<truncated>0</truncated>
		<difficult>0</difficult>
		<bndbox>
			<xmin>56</xmin>
			<ymin>145</ymin>
			<xmax>75</xmax>
			<ymax>178</ymax>
		</bndbox>
	</object>
	<object>
		<name>barrel</name>
		<pose>Unspecified</pose>
		<truncated>0</truncated>
		<difficult>0</difficult>
		<bndbox>
			<xmin>93</xmin>
			<ymin>141</ymin>
			<xmax>106</xmax>
			<ymax>169</ymax>
		</bndbox>
	</object>
	<object>
		<name>barrel</name>
		<pose>Unspecified</pose>
		<truncated>0</truncated>
		<difficult>0</difficult>
		<bndbox>
			<xmin>118</xmin>
			<ymin>140</ymin>
			<xmax>130</xmax>
			<ymax>164</ymax>
		</bndbox>
	</object>
	<object>
		<name>barrel</name>
		<pose>Unspecified</pose>
		<truncated>0</truncated>
		<difficult>0</difficult>
		<bndbox>
			<xmin>133</xmin>
			<ymin>140</ymin>
			<xmax>143</xmax>
			<ymax>159</ymax>
		</bndbox>
	</object>
	<object>
		<name>barrel</name>
		<pose>Unspecified</pose>
		<truncated>0</truncated>
		<difficult>0</difficult>
		<bndbox>
			<xmin>147</xmin>
			<ymin>137</ymin>
			<xmax>154</xmax>
			<ymax>157</ymax>
		</bndbox>
	</object>
	<object>
		<name>barrel</name>
		<pose>Unspecified</pose>
		<truncated>0</truncated>
		<difficult>0</difficult>
		<bndbox>
			<xmin>157</xmin>
			<ymin>136</ymin>
			<xmax>163</xmax>
			<ymax>153</ymax>
		</bndbox>
	</object>
	<object>
		<name>barrel</name>
		<pose>Unspecified</pose>
		<truncated>0</truncated>
		<difficult>0</difficult>
		<bndbox>
			<xmin>165</xmin>
			<ymin>136</ymin>
			<xmax>170</xmax>
			<ymax>152</ymax>
		</bndbox>
	</object>
	<object>
		<name>barrel</name>
		<pose>Unspecified</pose>
		<truncated>0</truncated>
		<difficult>0</difficult>
		<bndbox>
			<xmin>169</xmin>
			<ymin>134</ymin>
			<xmax>176</xmax>
			<ymax>149</ymax>
		</bndbox>
	</object>
	<object>
		<name>barrel</name>
		<pose>Unspecified</pose>
		<truncated>0</truncated>
		<difficult>0</difficult>
		<bndbox>
			<xmin>183</xmin>
			<ymin>129</ymin>
			<xmax>190</xmax>
			<ymax>144</ymax>
		</bndbox>
	</object>
	<object>
		<name>barrel</name>
		<pose>Unspecified</pose>
		<truncated>0</truncated>
		<difficult>0</difficult>
		<bndbox>
			<xmin>175</xmin>
			<ymin>135</ymin>
			<xmax>181</xmax>
			<ymax>145</ymax>
		</bndbox>
	</object>
	<object>
		<name>barrel</name>
		<pose>Unspecified</pose>
		<truncated>0</truncated>
		<difficult>0</difficult>
		<bndbox>
			<xmin>200</xmin>
			<ymin>125</ymin>
			<xmax>206</xmax>
			<ymax>139</ymax>
		</bndbox>
	</object>
	<object>
		<name>barrel</name>
		<pose>Unspecified</pose>
		<truncated>0</truncated>
		<difficult>0</difficult>
		<bndbox>
			<xmin>227</xmin>
			<ymin>127</ymin>
			<xmax>233</xmax>
			<ymax>138</ymax>
		</bndbox>
	</object>
	<object>
		<name>barrel</name>
		<pose>Unspecified</pose>
		<truncated>0</truncated>
		<difficult>0</difficult>
		<bndbox>
			<xmin>213</xmin>
			<ymin>127</ymin>
			<xmax>219</xmax>
			<ymax>138</ymax>
		</bndbox>
	</object>
	<object>
		<name>barrel</name>
		<pose>Unspecified</pose>
		<truncated>0</truncated>
		<difficult>0</difficult>
		<bndbox>
			<xmin>207</xmin>
			<ymin>125</ymin>
			<xmax>211</xmax>
			<ymax>132</ymax>
		</bndbox>
	</object>
</annotation>
